covid19/__init__.py
covid19/main.py
covid19/web/index.html
covid19_big/__init__.py
covid19_big/main.py
covid19_big/web/index.html
covid19_big/web/assets/index.html
covid19_big/web/assets/css/w3.css
covid19_big/web/assets/images/index.html
covid19_big/web/assets/images/logo-footer.png
covid19_big/web/assets/images/puskesmas.png
covid19_big/web/assets/js/chart.js
covid19_big/web/assets/js/index.html
covid19_big/web/assets/js/menu.js
covid19_big/web/assets/js/peta1.js
covid19_big/web/assets/js/peta10.js
covid19_big/web/assets/js/peta11.js
covid19_big/web/assets/js/peta12.js
covid19_big/web/assets/js/peta14.js
covid19_big/web/assets/js/peta15.js
covid19_big/web/assets/js/peta2.js
covid19_big/web/assets/js/peta3.js
covid19_big/web/assets/js/peta4.js
covid19_big/web/assets/js/peta5.js
covid19_big/web/assets/js/peta6.js
covid19_big/web/assets/js/peta7.js
covid19_big/web/assets/js/peta8.js
covid19_big/web/assets/js/peta9.js
covid19_big-1.0.0.dist-info/LICENSE
covid19_big-1.0.0.dist-info/METADATA
covid19_big-1.0.0.dist-info/WHEEL
covid19_big-1.0.0.dist-info/entry_points.txt
covid19_big-1.0.0.dist-info/top_level.txt
covid19_big-1.0.0.dist-info/RECORD
