Metadata-Version: 2.1
Name: covid19-big
Version: 1.0.0
Summary: A Covid19 BIG package
Home-page: https://github.com/emhayusa/covid19-big
Author: Muhammad Hasannudin Yusa
Author-email: emhayusa@gmail.com
License: UNKNOWN
Platform: UNKNOWN
Classifier: Programming Language :: Python :: 3
Classifier: License :: OSI Approved :: MIT License
Classifier: Operating System :: OS Independent
Requires-Dist: Click
